{
  "collapse-filter": false,
  "search": "",
  "showTags": true,
  "showAttachments": true,
  "hideUnresolved": true,
  "showOrphans": false,
  "collapse-color-groups": false,
  "colorGroups": [],
  "collapse-display": false,
  "showArrow": false,
  "textFadeMultiplier": 0,
  "nodeSizeMultiplier": 1.45260416666667,
  "lineSizeMultiplier": 0.559375,
  "collapse-forces": false,
  "centerStrength": 0,
  "repelStrength": 6.5625,
  "linkStrength": 0.494791666666667,
  "linkDistance": 500,
  "scale": 0.19753086419753085,
  "close": false
}