{
  "main": {
    "id": "4f32908455cbdb4a",
    "type": "split",
    "children": [
      {
        "id": "2c2a67e165a9a533",
        "type": "tabs",
        "children": [
          {
            "id": "ca740af6894f7444",
            "type": "leaf",
            "state": {
              "type": "markdown",
              "state": {
                "file": "lectures/Numerical Relativity Preliminaries.md",
                "mode": "source",
                "backlinks": true,
                "source": false
              },
              "icon": "lucide-file",
              "title": "Numerical Relativity Preliminaries"
            }
          },
          {
            "id": "730c3688f8527517",
            "type": "leaf",
            "state": {
              "type": "markdown",
              "state": {
                "file": "lectures/General Relativity Preliminaries.md",
                "mode": "source",
                "backlinks": true,
                "source": false
              },
              "icon": "lucide-file",
              "title": "General Relativity Preliminaries"
            }
          }
        ],
        "currentTab": 1
      }
    ],
    "direction": "vertical"
  },
  "left": {
    "id": "d481728967deb856",
    "type": "split",
    "children": [
      {
        "id": "63365e25f020a8dc",
        "type": "tabs",
        "children": [
          {
            "id": "c59c84ced1212cd7",
            "type": "leaf",
            "state": {
              "type": "file-explorer",
              "state": {
                "sortOrder": "alphabetical"
              },
              "icon": "lucide-folder-closed",
              "title": "Files"
            }
          },
          {
            "id": "3c53b34429401637",
            "type": "leaf",
            "state": {
              "type": "search",
              "state": {
                "query": "",
                "matchingCase": true,
                "explainSearch": false,
                "collapseAll": false,
                "extraContext": false,
                "sortOrder": "alphabetical"
              },
              "icon": "lucide-search",
              "title": "Search"
            }
          },
          {
            "id": "1441f36a36760fd0",
            "type": "leaf",
            "state": {
              "type": "bookmarks",
              "state": {},
              "icon": "lucide-bookmark",
              "title": "Bookmarks"
            }
          }
        ]
      }
    ],
    "direction": "horizontal",
    "width": 300
  },
  "right": {
    "id": "7f9f851c07e33842",
    "type": "split",
    "children": [
      {
        "id": "f97fb096df599c77",
        "type": "tabs",
        "dimension": 34.42340791738382,
        "children": [
          {
            "id": "cfc8d9526783dd42",
            "type": "leaf",
            "state": {
              "type": "backlink",
              "state": {
                "file": "docs/notes/numerical methods/Galerkin Method.md",
                "collapseAll": false,
                "extraContext": false,
                "sortOrder": "alphabetical",
                "showSearch": false,
                "searchQuery": "",
                "backlinkCollapsed": false,
                "unlinkedCollapsed": true
              },
              "icon": "links-coming-in",
              "title": "Backlinks for Galerkin Method"
            }
          },
          {
            "id": "da8e6828e916afbd",
            "type": "leaf",
            "state": {
              "type": "outgoing-link",
              "state": {
                "file": "docs/notes/numerical methods/Galerkin Method.md",
                "linksCollapsed": false,
                "unlinkedCollapsed": true
              },
              "icon": "links-going-out",
              "title": "Outgoing links from Galerkin Method"
            }
          },
          {
            "id": "6b6b443d2813612f",
            "type": "leaf",
            "state": {
              "type": "tag",
              "state": {
                "sortOrder": "frequency",
                "useHierarchy": true
              },
              "icon": "lucide-tags",
              "title": "Tags"
            }
          },
          {
            "id": "f21e71ac8ce70dce",
            "type": "leaf",
            "state": {
              "type": "outline",
              "state": {
                "file": "docs/notes/theoretical notes/General Relativistic Magnetohydrodynamics.md"
              },
              "icon": "lucide-list",
              "title": "Outline of General Relativistic Magnetohydrodynamics"
            }
          },
          {
            "id": "088f64965d4ea338",
            "type": "leaf",
            "state": {
              "type": "zotero-annotation-view",
              "state": {
                "file": "docs/notes/theoretical notes/General Relativistic Magnetohydrodynamics.md",
                "itemId": -1,
                "attachmentId": -1,
                "follow": "zt-reader"
              },
              "icon": "lucide-file",
              "title": "Plugin no longer active"
            }
          }
        ],
        "currentTab": 4
      },
      {
        "id": "f2018628ef7a3ad8",
        "type": "tabs",
        "dimension": 65.57659208261617,
        "children": [
          {
            "id": "506d534d269cea50",
            "type": "leaf",
            "state": {
              "type": "calendar",
              "state": {},
              "icon": "lucide-file",
              "title": "Plugin no longer active"
            }
          }
        ]
      }
    ],
    "direction": "horizontal",
    "width": 384.5,
    "collapsed": true
  },
  "left-ribbon": {
    "hiddenItems": {
      "switcher:Open quick switcher": false,
      "graph:Open graph view": false,
      "canvas:Create new canvas": false,
      "daily-notes:Open today's daily note": false,
      "templates:Insert template": false,
      "command-palette:Open command palette": false
    }
  },
  "active": "730c3688f8527517",
  "lastOpenFiles": [
    "lectures/Numerical Relativity Preliminaries.md",
    "lectures/General Relativity Preliminaries.md",
    "docs/notes/library overviews/NRPy+/Part1.2 - C outputs.md",
    "lectures",
    "docs/notes/library overviews/NRPy+/Part1.3 - Numerical Grids.md",
    "docs/notes/library overviews/NRPy+/Part1.1 - Scalar Wave Equation.md",
    "docs/notes/library overviews/NRPy+/Tutorial-Solving_the_Scalar_Wave_Equation_with_NumPy (2)/Tutorial-Solving_the_Scalar_Wave_Equation_with_NumPy.md",
    "docs/notes/library overviews/NRPy+/Tutorial-Solving_the_Scalar_Wave_Equation_with_NumPy (2)/output_42_2.png",
    "docs/notes/library overviews/NRPy+/Tutorial-Solving_the_Scalar_Wave_Equation_with_NumPy (2)",
    "docs/notes/library overviews/NRPy+/Tutorial-Solving_the_Scalar_Wave_Equation_with_NumPy/output_42_2.png",
    "docs/notes/library overviews/NRPy+/Tutorial-Solving_the_Scalar_Wave_Equation_with_NumPy/Tutorial-Solving_the_Scalar_Wave_Equation_with_NumPy.md",
    "docs/notes/library overviews/NRPy+/Tutorial-Solving_the_Scalar_Wave_Equation_with_NumPy",
    "docs/notes/library overviews/NRPy+/Tutorial-Solving_the_Scalar_Wave_Equation_with_NumPy.zip",
    "exportToHTML/Tutorial-Solving_the_Scalar_Wave_Equation_with_NumPy.ipynb.html",
    "exportToHTML",
    "docs/notes/library overviews/NRPy+/0 - Getting Started.md",
    "notebooks/educative/nrpy-tutorial/Tutorial-NRPyPlus_10_Minute_Overview.ipynb~",
    "notebooks/educative/nrpy-tutorial/texput.log",
    "notebooks/educative/nrpy-tutorial/tmp.txt",
    "notebooks/educative/nrpy-tutorial/__pycache__/var_access.cpython-312.pyc",
    "env/lib/python3.12/site-packages/notebook/static/be0a084962d8066884f7.svg",
    "env/lib/python3.12/site-packages/notebook/static/a3b9817780214caf01e8.svg",
    "env/lib/python3.12/site-packages/notebook/static/9674eb1bd55047179038.svg",
    "env/share/icons/hicolor/scalable/apps/notebook.svg",
    "env/share/icons/hicolor/scalable/apps/jupyterlab.svg",
    "env/share/jupyter/lab/static/be0a084962d8066884f7.svg",
    "env/share/jupyter/lab/static/a3b9817780214caf01e8.svg",
    "env/share/jupyter/lab/static/9674eb1bd55047179038.svg",
    "env/lib/python3.12/site-packages/jupyter_server/i18n/README.md",
    "env/lib/python3.12/site-packages/nbconvert/templates/skeleton/README.md",
    "env/lib/python3.12/site-packages/nbconvert/templates/README.md",
    "env/lib/python3.12/site-packages/httpx-0.27.2.dist-info/licenses/LICENSE.md",
    "env/lib/python3.12/site-packages/httpcore-1.0.7.dist-info/licenses/LICENSE.md",
    "env/lib/python3.12/site-packages/idna-3.10.dist-info/LICENSE.md",
    "env/lib/python3.12/site-packages/soupsieve-2.6.dist-info/licenses/LICENSE.md",
    "env/lib/python3.12/site-packages/debugpy/_vendored/pydevd/pydevd_plugins/extensions/README.md",
    "env/lib/python3.12/site-packages/zmq/backend/cffi/README.md",
    "env/lib/python3.12/site-packages/pyzmq-26.2.0.dist-info/licenses/LICENSE.md",
    "docs/notes/theoretical notes/General Relativistic Magnetohydrodynamics.md",
    "docs/notes/theoretical notes/The 3+1 Valencia formulation of GRMHD equations for numerical relativity.md",
    "docs/notes/theoretical notes/Special Relativity.md",
    "docs/notes/theoretical notes/Relativistic Hydrodynamics.md",
    "docs/notes/numerical methods/Conservative Finite Difference Method.md",
    "docs/notes/numerical methods/Discontinuous Galerkin Method.md",
    "docs/notes/numerical methods/Galerkin Method.md",
    "docs/notes/theoretical notes/3+1 Decomposition.md",
    "Untitled.canvas",
    "docs/notes/Untitled.canvas"
  ]
}